edmkit/__init__.py
edmkit/ccm.py
edmkit/embedding.py
edmkit/simplex_projection.py
edmkit/smap.py
edmkit/tensor.py
edmkit/util.py
edmkit/generate/__init__.py
edmkit/generate/double_pendulum.py
edmkit/generate/lorenz.py
edmkit/generate/mackey_glass.py
edmkit-0.0.0.dist-info/METADATA
edmkit-0.0.0.dist-info/WHEEL
edmkit-0.0.0.dist-info/licenses/LICENSE
edmkit-0.0.0.dist-info/RECORD
