Metadata-Version: 2.4
Name: edmkit
Version: 0.0.0
Summary: Simple EDM (Empirical Dynamic Modeling) library
Author-email: FUJISHIGE TEMMA <tenma.x0@gmail.com>
License-File: LICENSE
Requires-Python: >=3.13
Requires-Dist: numpy>=2.3.4
Requires-Dist: tinygrad>=0.11.0
